{
  "bundle_schema_version": "dediren-bundle.schema.v1",
  "product": "dediren",
  "version": "0.1.2",
  "target": "x86_64-unknown-linux-gnu",
  "built_at_utc": "2026-05-12T15:33:18Z",
  "plugins": [
    { "id": "generic-graph", "version": "0.1.2" },
    { "id": "elk-layout", "version": "0.1.2" },
    { "id": "svg-render", "version": "0.1.2" },
    { "id": "archimate-oef", "version": "0.1.2" }
  ],
  "schemas_dir": "schemas",
  "fixtures_dir": "fixtures",
  "elk_helper": "runtimes/elk-layout-java/bin/dediren-elk-layout-java"
}
